llnl_thicket-2026.1.0.dist-info/licenses/LICENSE
llnl_thicket-2026.1.0.dist-info/licenses/NOTICE
thicket/__init__.py
thicket/ensemble.py
thicket/groupby.py
thicket/helpers.py
thicket/model_extrap.py
thicket/ncu.py
thicket/query.py
thicket/thicket.py
thicket/utils.py
thicket/version.py
thicket/external/__init__.py
thicket/external/console.py
thicket/stats/__init__.py
thicket/stats/calc_boxplot_statistics.py
thicket/stats/calc_temporal_pattern.py
thicket/stats/check_normality.py
thicket/stats/confidence_interval.py
thicket/stats/correlation_nodewise.py
thicket/stats/display_boxplot.py
thicket/stats/display_heatmap.py
thicket/stats/display_histogram.py
thicket/stats/display_violinplot.py
thicket/stats/distance.py
thicket/stats/maximum.py
thicket/stats/mean.py
thicket/stats/median.py
thicket/stats/minimum.py
thicket/stats/percentiles.py
thicket/stats/preference.py
thicket/stats/scoring.py
thicket/stats/stats_utils.py
thicket/stats/std.py
thicket/stats/sum.py
thicket/stats/ttest.py
thicket/stats/variance.py
thicket/vis/__init__.py
thicket/vis/package.json
thicket/vis/static_fixer.py
thicket/vis/visualizations.py
thicket/vis/webpack.config.js
thicket/vis/scripts/globals.js
thicket/vis/scripts/treetable.js
thicket/vis/scripts/pcp/datautil.js
thicket/vis/scripts/pcp/globals.js
thicket/vis/scripts/pcp/pcp.js
thicket/vis/scripts/pcp/scatter.js
thicket/vis/scripts/pcp/stackedarea.js
thicket/vis/scripts/pcp/store.js
thicket/vis/scripts/topdown/stackedbars.js
thicket/vis/scripts/topdown/topdown.js
thicket/vis/static/pcp_bundle.html
thicket/vis/static/pcp_bundle.js
thicket/vis/static/topdown_bundle.html
thicket/vis/static/topdown_bundle.js
thicket/vis/static/treetable_bundle.html
thicket/vis/static/treetable_bundle.js
thicket/vis/templates/pcp.html
thicket/vis/templates/topdown.html
thicket/vis/templates/treetable.html
llnl_thicket-2026.1.0.dist-info/METADATA
llnl_thicket-2026.1.0.dist-info/WHEEL
llnl_thicket-2026.1.0.dist-info/top_level.txt
llnl_thicket-2026.1.0.dist-info/RECORD
