Metadata-Version: 2.4
Name: llnl-thicket
Version: 2026.1.0
Summary: Toolkit for exploratory data analysis of ensemble performance data
License: MIT
Project-URL: Source Code, https://github.com/LLNL/thicket
Project-URL: Documentation, https://thicket.readthedocs.io/
Requires-Python: >=3.6.1
License-File: LICENSE
License-File: NOTICE
Requires-Dist: scipy
Requires-Dist: numpy
Requires-Dist: pandas>=1.1
Requires-Dist: llnl-hatchet
Requires-Dist: tqdm
Requires-Dist: more-itertools
Provides-Extra: extrap
Requires-Dist: extrap; extra == "extrap"
Requires-Dist: matplotlib; extra == "extrap"
Provides-Extra: plotting
Requires-Dist: seaborn; extra == "plotting"
Provides-Extra: vis
Requires-Dist: beautifulsoup4; extra == "vis"
Dynamic: description
Dynamic: description-content-type
Dynamic: keywords
Dynamic: license
Dynamic: license-file
Dynamic: project-url
Dynamic: provides-extra
Dynamic: requires-dist
Dynamic: requires-python
Dynamic: summary
